global_pinger.py
global_pinger-0.1.2.dist-info/LICENSE
global_pinger-0.1.2.dist-info/METADATA
global_pinger-0.1.2.dist-info/WHEEL
global_pinger-0.1.2.dist-info/top_level.txt
global_pinger-0.1.2.dist-info/RECORD
