Metadata-Version: 2.1
Name: global-pinger
Version: 0.1.2
Summary: A pinger that can be used globally to send ICMP requests
Author-email: zer0ul <zer0ul@vulnium.com>
Project-URL: Homepage, https://github.com/pypa/sampleproject
Project-URL: Bug Tracker, https://github.com/pypa/sampleproject/issues
Classifier: Programming Language :: Python :: 3
Classifier: License :: OSI Approved :: MIT License
Classifier: Operating System :: OS Independent
Requires-Python: >=3.7
License-File: LICENSE
